nyuctf/__init__.py
nyuctf/__main__.py
nyuctf/challenge.py
nyuctf/dataset.py
nyuctf/download.py
nyuctf/utils.py
nyuctf-1.1.1.dist-info/METADATA
nyuctf-1.1.1.dist-info/WHEEL
nyuctf-1.1.1.dist-info/RECORD
