Metadata-Version: 2.4
Name: nyuctf
Version: 1.1.1
Summary: NYU CTF Dataset loader package
Project-URL: Homepage, https://nyu-llm-ctf.github.io
Author-email: NYU CTF <nyuctf@gmail.com>, Meet Udeshi <m.udeshi@nyu.edu>
Classifier: License :: OSI Approved :: Apache Software License
Classifier: Operating System :: OS Independent
Classifier: Programming Language :: Python :: 3
Requires-Python: >=3.8
Requires-Dist: pathlib
